nonebot_plugin_batarot-0.2.2.post5.dist-info/METADATA
nonebot_plugin_batarot-0.2.2.post5.dist-info/WHEEL
nonebot_plugin_batarot-0.2.2.post5.dist-info/entry_points.txt
nonebot_plugin_batarot-0.2.2.post5.dist-info/licenses/LICENSE
nonebot_plugin_batarot/__init__.py
nonebot_plugin_batarot/batarot.json
nonebot_plugin_batarot/batarot_fortune.json
nonebot_plugin_batarot/batarot_spread.json
nonebot_plugin_batarot/batarot_url.json
nonebot_plugin_batarot/commands.py
nonebot_plugin_batarot/config.py
nonebot_plugin_batarot/handler.py
nonebot_plugin_batarot/image/0-愚者.png
nonebot_plugin_batarot/image/01-魔术师.png
nonebot_plugin_batarot/image/02-女祭司.png
nonebot_plugin_batarot/image/03-女皇.png
nonebot_plugin_batarot/image/04-皇帝.png
nonebot_plugin_batarot/image/05-教皇.png
nonebot_plugin_batarot/image/06-恋人.png
nonebot_plugin_batarot/image/07-战车.png
nonebot_plugin_batarot/image/08-力量.png
nonebot_plugin_batarot/image/09-隐士.png
nonebot_plugin_batarot/image/10-命运之轮.png
nonebot_plugin_batarot/image/11-正义.png
nonebot_plugin_batarot/image/12-倒吊人.png
nonebot_plugin_batarot/image/13-死神.png
nonebot_plugin_batarot/image/14-节制.png
nonebot_plugin_batarot/image/15-恶魔.png
nonebot_plugin_batarot/image/16-高塔.png
nonebot_plugin_batarot/image/17-星星.png
nonebot_plugin_batarot/image/18-月亮.png
nonebot_plugin_batarot/image/19-太阳.png
nonebot_plugin_batarot/image/20-审判.png
nonebot_plugin_batarot/image/21-世界.png
nonebot_plugin_batarot/utils.py
nonebot_plugin_batarot-0.2.2.post5.dist-info/RECORD
