Metadata-Version: 2.1
Name: nonebot-plugin-batarot
Version: 0.2.2.post5
Summary: A nonebot2 plugin for Blue Archive Tarot.
Keywords: blue archive,tarot,nonebot,nonebot2,bot,qq
Home-page: https://github.com/Perseus037/nonebot_plugin_batarot/
Author-Email: Perseus037 <1209228678@qq.com>
License: MIT
Classifier: Natural Language :: Chinese (Simplified)
Classifier: Topic :: Communications
Classifier: Topic :: Communications :: Chat
Classifier: Topic :: Games/Entertainment
Classifier: Topic :: Internet
Classifier: Topic :: Internet :: WWW/HTTP
Classifier: Topic :: Internet :: WWW/HTTP :: Dynamic Content
Project-URL: Homepage, https://github.com/Perseus037/nonebot_plugin_batarot/
Requires-Python: <4.0,>=3.8
Requires-Dist: nonebot2>=2.1.1
Requires-Dist: pydantic>=1.10.13
Requires-Dist: nonebot-adapter-onebot>=2.3.1
Requires-Dist: nonebot-plugin-htmlrender>=0.2.2
Requires-Dist: nonebot-plugin-apscheduler>=0.3.0
Requires-Dist: nonebot-plugin-send-anything-anywhere>=0.4.0
Requires-Dist: aiohttp>=3.9.1
Provides-Extra: menu
Requires-Dist: nonebot-plugin-PicMenu>=0.2; extra == "menu"
